herpai_lib-0.1.0.dist-info/licenses/LICENSE
src/__init__.py
src/__version__.py
src/cli.py
herpai_lib-0.1.0.dist-info/METADATA
herpai_lib-0.1.0.dist-info/WHEEL
herpai_lib-0.1.0.dist-info/top_level.txt
herpai_lib-0.1.0.dist-info/RECORD
