Metadata-Version: 2.4
Name: herpai-lib
Version: 0.1.0
Summary: HerpAI Core Library, Accelerating the discovery of a functional cure for HSV-1 and HSV-2 using AI.
Author-email: OpenBioCure Contributors <openbiocure@gmail.com>
License: MIT
Requires-Python: >=3.9
License-File: LICENSE
Requires-Dist: sqlalchemy>=2.0.0
Requires-Dist: pyyaml>=6.0
Requires-Dist: aiosqlite>=0.17.0
Provides-Extra: dev
Requires-Dist: pytest>=7.0.0; extra == "dev"
Requires-Dist: pytest-asyncio>=0.18.0; extra == "dev"
Requires-Dist: pytest-cov>=4.0.0; extra == "dev"
Requires-Dist: black; extra == "dev"
Requires-Dist: isort; extra == "dev"
Requires-Dist: mypy; extra == "dev"
Requires-Dist: pre-commit; extra == "dev"
Dynamic: license-file
